flutterpy/__init__.py
flutterpy/criticalspeed/__init__.py
flutterpy/derivatives/__init__.py
flutterpy/derivatives/flutter_derivatives.py
flutterpy/derivatives/independent_functions.py
flutterpy/derivatives/sinusoidal_utilities.py
flutterpy/derivatives/calculators/__init__.py
flutterpy/derivatives/notations/__init__.py
flutterpy/derivatives/notations/_notation_definition.py
flutterpy/derivatives/notations/notation.py
flutterpy/plot/__init__.py
flutterpy/plot/plot_utilities.py
flutterpy/structure/__init__.py
flutterpy-0.0.0.dist-info/LICENSE
flutterpy-0.0.0.dist-info/METADATA
flutterpy-0.0.0.dist-info/WHEEL
flutterpy-0.0.0.dist-info/top_level.txt
flutterpy-0.0.0.dist-info/RECORD
